{"url": "https://afltables.com/afl/stats/games/1998/010719980919.html", "fetched_at": 1761708449, "token": "010719980919.html_f3cb142d", "html_path": "data\\raw\\cache\\html\\010719980919.html_f3cb142d.html", "tables": ["data\\raw\\cache\\tables\\010719980919.html_f3cb142d_tbl0.csv", "data\\raw\\cache\\tables\\010719980919.html_f3cb142d_tbl1.csv", "data\\raw\\cache\\tables\\010719980919.html_f3cb142d_tbl2.csv", "data\\raw\\cache\\tables\\010719980919.html_f3cb142d_tbl3.csv", "data\\raw\\cache\\tables\\010719980919.html_f3cb142d_tbl4.csv", "data\\raw\\cache\\tables\\010719980919.html_f3cb142d_tbl5.csv", "data\\raw\\cache\\tables\\010719980919.html_f3cb142d_tbl6.csv"]}