{"url": "https://afltables.com/afl/stats/games/2012/010920120728.html", "fetched_at": 1769059615, "token": "010920120728.html_484f4ad9", "html_path": "data\\raw\\cache\\html\\010920120728.html_484f4ad9.html", "tables": ["data\\raw\\cache\\tables\\010920120728.html_484f4ad9_tbl0.csv", "data\\raw\\cache\\tables\\010920120728.html_484f4ad9_tbl1.csv", "data\\raw\\cache\\tables\\010920120728.html_484f4ad9_tbl2.csv", "data\\raw\\cache\\tables\\010920120728.html_484f4ad9_tbl3.csv", "data\\raw\\cache\\tables\\010920120728.html_484f4ad9_tbl4.csv", "data\\raw\\cache\\tables\\010920120728.html_484f4ad9_tbl5.csv", "data\\raw\\cache\\tables\\010920120728.html_484f4ad9_tbl6.csv", "data\\raw\\cache\\tables\\010920120728.html_484f4ad9_tbl7.csv"]}