{"url": "https://afltables.com/afl/stats/games/2016/011220160326.html", "fetched_at": 1769070532, "token": "011220160326.html_fab103e6", "html_path": "data\\raw\\cache\\html\\011220160326.html_fab103e6.html", "tables": ["data\\raw\\cache\\tables\\011220160326.html_fab103e6_tbl0.csv", "data\\raw\\cache\\tables\\011220160326.html_fab103e6_tbl1.csv", "data\\raw\\cache\\tables\\011220160326.html_fab103e6_tbl2.csv", "data\\raw\\cache\\tables\\011220160326.html_fab103e6_tbl3.csv", "data\\raw\\cache\\tables\\011220160326.html_fab103e6_tbl4.csv", "data\\raw\\cache\\tables\\011220160326.html_fab103e6_tbl5.csv", "data\\raw\\cache\\tables\\011220160326.html_fab103e6_tbl6.csv", "data\\raw\\cache\\tables\\011220160326.html_fab103e6_tbl7.csv"]}