{"url": "https://afltables.com/afl/stats/games/2005/011420050618.html", "fetched_at": 1768778021, "token": "011420050618.html_c903d144", "html_path": "data\\raw\\cache\\html\\011420050618.html_c903d144.html", "tables": ["data\\raw\\cache\\tables\\011420050618.html_c903d144_tbl0.csv", "data\\raw\\cache\\tables\\011420050618.html_c903d144_tbl1.csv", "data\\raw\\cache\\tables\\011420050618.html_c903d144_tbl2.csv", "data\\raw\\cache\\tables\\011420050618.html_c903d144_tbl3.csv", "data\\raw\\cache\\tables\\011420050618.html_c903d144_tbl4.csv", "data\\raw\\cache\\tables\\011420050618.html_c903d144_tbl5.csv", "data\\raw\\cache\\tables\\011420050618.html_c903d144_tbl6.csv", "data\\raw\\cache\\tables\\011420050618.html_c903d144_tbl7.csv"]}