{"url": "https://afltables.com/afl/stats/games/1991/020519910810.html", "fetched_at": 1761707077, "token": "020519910810.html_3b39e652", "html_path": "data\\raw\\cache\\html\\020519910810.html_3b39e652.html", "tables": ["data\\raw\\cache\\tables\\020519910810.html_3b39e652_tbl0.csv", "data\\raw\\cache\\tables\\020519910810.html_3b39e652_tbl1.csv", "data\\raw\\cache\\tables\\020519910810.html_3b39e652_tbl2.csv", "data\\raw\\cache\\tables\\020519910810.html_3b39e652_tbl3.csv", "data\\raw\\cache\\tables\\020519910810.html_3b39e652_tbl4.csv", "data\\raw\\cache\\tables\\020519910810.html_3b39e652_tbl5.csv", "data\\raw\\cache\\tables\\020519910810.html_3b39e652_tbl6.csv"]}