{"url": "https://afltables.com/afl/stats/games/1999/030719990801.html", "fetched_at": 1761709405, "token": "030719990801.html_b1cc7650", "html_path": "data\\raw\\cache\\html\\030719990801.html_b1cc7650.html", "tables": ["data\\raw\\cache\\tables\\030719990801.html_b1cc7650_tbl0.csv", "data\\raw\\cache\\tables\\030719990801.html_b1cc7650_tbl1.csv", "data\\raw\\cache\\tables\\030719990801.html_b1cc7650_tbl2.csv", "data\\raw\\cache\\tables\\030719990801.html_b1cc7650_tbl3.csv", "data\\raw\\cache\\tables\\030719990801.html_b1cc7650_tbl4.csv", "data\\raw\\cache\\tables\\030719990801.html_b1cc7650_tbl5.csv", "data\\raw\\cache\\tables\\030719990801.html_b1cc7650_tbl6.csv"]}