{"url": "https://afltables.com/afl/stats/games/2023/030820230709.html", "fetched_at": 1769074734, "token": "030820230709.html_57d3bcd1", "html_path": "data\\raw\\cache\\html\\030820230709.html_57d3bcd1.html", "tables": ["data\\raw\\cache\\tables\\030820230709.html_57d3bcd1_tbl0.csv", "data\\raw\\cache\\tables\\030820230709.html_57d3bcd1_tbl1.csv", "data\\raw\\cache\\tables\\030820230709.html_57d3bcd1_tbl2.csv", "data\\raw\\cache\\tables\\030820230709.html_57d3bcd1_tbl3.csv", "data\\raw\\cache\\tables\\030820230709.html_57d3bcd1_tbl4.csv", "data\\raw\\cache\\tables\\030820230709.html_57d3bcd1_tbl5.csv", "data\\raw\\cache\\tables\\030820230709.html_57d3bcd1_tbl6.csv", "data\\raw\\cache\\tables\\030820230709.html_57d3bcd1_tbl7.csv"]}