{"url": "https://afltables.com/afl/stats/games/2005/030920050513.html", "fetched_at": 1768777942, "token": "030920050513.html_7e6bfec3", "html_path": "data\\raw\\cache\\html\\030920050513.html_7e6bfec3.html", "tables": ["data\\raw\\cache\\tables\\030920050513.html_7e6bfec3_tbl0.csv", "data\\raw\\cache\\tables\\030920050513.html_7e6bfec3_tbl1.csv", "data\\raw\\cache\\tables\\030920050513.html_7e6bfec3_tbl2.csv", "data\\raw\\cache\\tables\\030920050513.html_7e6bfec3_tbl3.csv", "data\\raw\\cache\\tables\\030920050513.html_7e6bfec3_tbl4.csv", "data\\raw\\cache\\tables\\030920050513.html_7e6bfec3_tbl5.csv", "data\\raw\\cache\\tables\\030920050513.html_7e6bfec3_tbl6.csv", "data\\raw\\cache\\tables\\030920050513.html_7e6bfec3_tbl7.csv"]}