{"url": "https://afltables.com/afl/stats/games/2008/031420080320.html", "fetched_at": 1769046231, "token": "031420080320.html_92417968", "html_path": "data\\raw\\cache\\html\\031420080320.html_92417968.html", "tables": ["data\\raw\\cache\\tables\\031420080320.html_92417968_tbl0.csv", "data\\raw\\cache\\tables\\031420080320.html_92417968_tbl1.csv", "data\\raw\\cache\\tables\\031420080320.html_92417968_tbl2.csv", "data\\raw\\cache\\tables\\031420080320.html_92417968_tbl3.csv", "data\\raw\\cache\\tables\\031420080320.html_92417968_tbl4.csv", "data\\raw\\cache\\tables\\031420080320.html_92417968_tbl5.csv", "data\\raw\\cache\\tables\\031420080320.html_92417968_tbl6.csv", "data\\raw\\cache\\tables\\031420080320.html_92417968_tbl7.csv"]}