{"url": "https://afltables.com/afl/stats/games/2010/031820100530.html", "fetched_at": 1769047224, "token": "031820100530.html_7e12503e", "html_path": "data\\raw\\cache\\html\\031820100530.html_7e12503e.html", "tables": ["data\\raw\\cache\\tables\\031820100530.html_7e12503e_tbl0.csv", "data\\raw\\cache\\tables\\031820100530.html_7e12503e_tbl1.csv", "data\\raw\\cache\\tables\\031820100530.html_7e12503e_tbl2.csv", "data\\raw\\cache\\tables\\031820100530.html_7e12503e_tbl3.csv", "data\\raw\\cache\\tables\\031820100530.html_7e12503e_tbl4.csv", "data\\raw\\cache\\tables\\031820100530.html_7e12503e_tbl5.csv", "data\\raw\\cache\\tables\\031820100530.html_7e12503e_tbl6.csv", "data\\raw\\cache\\tables\\031820100530.html_7e12503e_tbl7.csv"]}