{"url": "https://afltables.com/afl/stats/games/2025/032020250809.html", "fetched_at": 1769075732, "token": "032020250809.html_c0b52a9f", "html_path": "data\\raw\\cache\\html\\032020250809.html_c0b52a9f.html", "tables": ["data\\raw\\cache\\tables\\032020250809.html_c0b52a9f_tbl0.csv", "data\\raw\\cache\\tables\\032020250809.html_c0b52a9f_tbl1.csv", "data\\raw\\cache\\tables\\032020250809.html_c0b52a9f_tbl2.csv", "data\\raw\\cache\\tables\\032020250809.html_c0b52a9f_tbl3.csv", "data\\raw\\cache\\tables\\032020250809.html_c0b52a9f_tbl4.csv", "data\\raw\\cache\\tables\\032020250809.html_c0b52a9f_tbl5.csv", "data\\raw\\cache\\tables\\032020250809.html_c0b52a9f_tbl6.csv", "data\\raw\\cache\\tables\\032020250809.html_c0b52a9f_tbl7.csv"]}