{"url": "https://afltables.com/afl/stats/games/2013/041320130907.html", "fetched_at": 1769060183, "token": "041320130907.html_650e4021", "html_path": "data\\raw\\cache\\html\\041320130907.html_650e4021.html", "tables": ["data\\raw\\cache\\tables\\041320130907.html_650e4021_tbl0.csv", "data\\raw\\cache\\tables\\041320130907.html_650e4021_tbl1.csv", "data\\raw\\cache\\tables\\041320130907.html_650e4021_tbl2.csv", "data\\raw\\cache\\tables\\041320130907.html_650e4021_tbl3.csv", "data\\raw\\cache\\tables\\041320130907.html_650e4021_tbl4.csv", "data\\raw\\cache\\tables\\041320130907.html_650e4021_tbl5.csv", "data\\raw\\cache\\tables\\041320130907.html_650e4021_tbl6.csv", "data\\raw\\cache\\tables\\041320130907.html_650e4021_tbl7.csv"]}