{"url": "https://afltables.com/afl/stats/games/1999/041919990828.html", "fetched_at": 1761711066, "token": "041919990828.html_42cbd651", "html_path": "data\\raw\\cache\\html\\041919990828.html_42cbd651.html", "tables": ["data\\raw\\cache\\tables\\041919990828.html_42cbd651_tbl0.csv", "data\\raw\\cache\\tables\\041919990828.html_42cbd651_tbl1.csv", "data\\raw\\cache\\tables\\041919990828.html_42cbd651_tbl2.csv", "data\\raw\\cache\\tables\\041919990828.html_42cbd651_tbl3.csv", "data\\raw\\cache\\tables\\041919990828.html_42cbd651_tbl4.csv", "data\\raw\\cache\\tables\\041919990828.html_42cbd651_tbl5.csv", "data\\raw\\cache\\tables\\041919990828.html_42cbd651_tbl6.csv"]}