{"url": "https://afltables.com/afl/stats/games/2012/050820120623.html", "fetched_at": 1769059538, "token": "050820120623.html_c37b1ef2", "html_path": "data\\raw\\cache\\html\\050820120623.html_c37b1ef2.html", "tables": ["data\\raw\\cache\\tables\\050820120623.html_c37b1ef2_tbl0.csv", "data\\raw\\cache\\tables\\050820120623.html_c37b1ef2_tbl1.csv", "data\\raw\\cache\\tables\\050820120623.html_c37b1ef2_tbl2.csv", "data\\raw\\cache\\tables\\050820120623.html_c37b1ef2_tbl3.csv", "data\\raw\\cache\\tables\\050820120623.html_c37b1ef2_tbl4.csv", "data\\raw\\cache\\tables\\050820120623.html_c37b1ef2_tbl5.csv", "data\\raw\\cache\\tables\\050820120623.html_c37b1ef2_tbl6.csv", "data\\raw\\cache\\tables\\050820120623.html_c37b1ef2_tbl7.csv"]}