{"url": "https://afltables.com/afl/stats/games/2011/050920110702.html", "fetched_at": 1769059147, "token": "050920110702.html_08b39652", "html_path": "data\\raw\\cache\\html\\050920110702.html_08b39652.html", "tables": ["data\\raw\\cache\\tables\\050920110702.html_08b39652_tbl0.csv", "data\\raw\\cache\\tables\\050920110702.html_08b39652_tbl1.csv", "data\\raw\\cache\\tables\\050920110702.html_08b39652_tbl2.csv", "data\\raw\\cache\\tables\\050920110702.html_08b39652_tbl3.csv", "data\\raw\\cache\\tables\\050920110702.html_08b39652_tbl4.csv", "data\\raw\\cache\\tables\\050920110702.html_08b39652_tbl5.csv", "data\\raw\\cache\\tables\\050920110702.html_08b39652_tbl6.csv", "data\\raw\\cache\\tables\\050920110702.html_08b39652_tbl7.csv"]}