{"url": "https://afltables.com/afl/stats/games/2004/050920040522.html", "fetched_at": 1768777561, "token": "050920040522.html_0633886a", "html_path": "data\\raw\\cache\\html\\050920040522.html_0633886a.html", "tables": ["data\\raw\\cache\\tables\\050920040522.html_0633886a_tbl0.csv", "data\\raw\\cache\\tables\\050920040522.html_0633886a_tbl1.csv", "data\\raw\\cache\\tables\\050920040522.html_0633886a_tbl2.csv", "data\\raw\\cache\\tables\\050920040522.html_0633886a_tbl3.csv", "data\\raw\\cache\\tables\\050920040522.html_0633886a_tbl4.csv", "data\\raw\\cache\\tables\\050920040522.html_0633886a_tbl5.csv", "data\\raw\\cache\\tables\\050920040522.html_0633886a_tbl6.csv", "data\\raw\\cache\\tables\\050920040522.html_0633886a_tbl7.csv"]}