{"url": "https://afltables.com/afl/stats/games/2002/051320020913.html", "fetched_at": 1768776974, "token": "051320020913.html_dc759068", "html_path": "data\\raw\\cache\\html\\051320020913.html_dc759068.html", "tables": ["data\\raw\\cache\\tables\\051320020913.html_dc759068_tbl0.csv", "data\\raw\\cache\\tables\\051320020913.html_dc759068_tbl1.csv", "data\\raw\\cache\\tables\\051320020913.html_dc759068_tbl2.csv", "data\\raw\\cache\\tables\\051320020913.html_dc759068_tbl3.csv", "data\\raw\\cache\\tables\\051320020913.html_dc759068_tbl4.csv", "data\\raw\\cache\\tables\\051320020913.html_dc759068_tbl5.csv", "data\\raw\\cache\\tables\\051320020913.html_dc759068_tbl6.csv", "data\\raw\\cache\\tables\\051320020913.html_dc759068_tbl7.csv"]}