{"url": "https://afltables.com/afl/stats/games/2024/051420240525.html", "fetched_at": 1769075106, "token": "051420240525.html_9ddc80a2", "html_path": "data\\raw\\cache\\html\\051420240525.html_9ddc80a2.html", "tables": ["data\\raw\\cache\\tables\\051420240525.html_9ddc80a2_tbl0.csv", "data\\raw\\cache\\tables\\051420240525.html_9ddc80a2_tbl1.csv", "data\\raw\\cache\\tables\\051420240525.html_9ddc80a2_tbl2.csv", "data\\raw\\cache\\tables\\051420240525.html_9ddc80a2_tbl3.csv", "data\\raw\\cache\\tables\\051420240525.html_9ddc80a2_tbl4.csv", "data\\raw\\cache\\tables\\051420240525.html_9ddc80a2_tbl5.csv", "data\\raw\\cache\\tables\\051420240525.html_9ddc80a2_tbl6.csv", "data\\raw\\cache\\tables\\051420240525.html_9ddc80a2_tbl7.csv"]}