{"url": "https://afltables.com/afl/stats/games/2025/070920250522.html", "fetched_at": 1769075543, "token": "070920250522.html_32f29a32", "html_path": "data\\raw\\cache\\html\\070920250522.html_32f29a32.html", "tables": ["data\\raw\\cache\\tables\\070920250522.html_32f29a32_tbl0.csv", "data\\raw\\cache\\tables\\070920250522.html_32f29a32_tbl1.csv", "data\\raw\\cache\\tables\\070920250522.html_32f29a32_tbl2.csv", "data\\raw\\cache\\tables\\070920250522.html_32f29a32_tbl3.csv", "data\\raw\\cache\\tables\\070920250522.html_32f29a32_tbl4.csv", "data\\raw\\cache\\tables\\070920250522.html_32f29a32_tbl5.csv", "data\\raw\\cache\\tables\\070920250522.html_32f29a32_tbl6.csv", "data\\raw\\cache\\tables\\070920250522.html_32f29a32_tbl7.csv"]}