{"url": "https://afltables.com/afl/stats/games/1998/071519980627.html", "fetched_at": 1761708303, "token": "071519980627.html_21229033", "html_path": "data\\raw\\cache\\html\\071519980627.html_21229033.html", "tables": ["data\\raw\\cache\\tables\\071519980627.html_21229033_tbl0.csv", "data\\raw\\cache\\tables\\071519980627.html_21229033_tbl1.csv", "data\\raw\\cache\\tables\\071519980627.html_21229033_tbl2.csv", "data\\raw\\cache\\tables\\071519980627.html_21229033_tbl3.csv", "data\\raw\\cache\\tables\\071519980627.html_21229033_tbl4.csv", "data\\raw\\cache\\tables\\071519980627.html_21229033_tbl5.csv", "data\\raw\\cache\\tables\\071519980627.html_21229033_tbl6.csv"]}