{"url": "https://afltables.com/afl/stats/games/2023/080920230520.html", "fetched_at": 1769074618, "token": "080920230520.html_89cdbac8", "html_path": "data\\raw\\cache\\html\\080920230520.html_89cdbac8.html", "tables": ["data\\raw\\cache\\tables\\080920230520.html_89cdbac8_tbl0.csv", "data\\raw\\cache\\tables\\080920230520.html_89cdbac8_tbl1.csv", "data\\raw\\cache\\tables\\080920230520.html_89cdbac8_tbl2.csv", "data\\raw\\cache\\tables\\080920230520.html_89cdbac8_tbl3.csv", "data\\raw\\cache\\tables\\080920230520.html_89cdbac8_tbl4.csv", "data\\raw\\cache\\tables\\080920230520.html_89cdbac8_tbl5.csv", "data\\raw\\cache\\tables\\080920230520.html_89cdbac8_tbl6.csv", "data\\raw\\cache\\tables\\080920230520.html_89cdbac8_tbl7.csv"]}