{"url": "https://afltables.com/afl/stats/games/2016/081820160807.html", "fetched_at": 1769070995, "token": "081820160807.html_7064e9fa", "html_path": "data\\raw\\cache\\html\\081820160807.html_7064e9fa.html", "tables": ["data\\raw\\cache\\tables\\081820160807.html_7064e9fa_tbl0.csv", "data\\raw\\cache\\tables\\081820160807.html_7064e9fa_tbl1.csv", "data\\raw\\cache\\tables\\081820160807.html_7064e9fa_tbl2.csv", "data\\raw\\cache\\tables\\081820160807.html_7064e9fa_tbl3.csv", "data\\raw\\cache\\tables\\081820160807.html_7064e9fa_tbl4.csv", "data\\raw\\cache\\tables\\081820160807.html_7064e9fa_tbl5.csv", "data\\raw\\cache\\tables\\081820160807.html_7064e9fa_tbl6.csv", "data\\raw\\cache\\tables\\081820160807.html_7064e9fa_tbl7.csv"]}