{"url": "https://afltables.com/afl/stats/games/2014/081920140621.html", "fetched_at": 1769060476, "token": "081920140621.html_df371131", "html_path": "data\\raw\\cache\\html\\081920140621.html_df371131.html", "tables": ["data\\raw\\cache\\tables\\081920140621.html_df371131_tbl0.csv", "data\\raw\\cache\\tables\\081920140621.html_df371131_tbl1.csv", "data\\raw\\cache\\tables\\081920140621.html_df371131_tbl2.csv", "data\\raw\\cache\\tables\\081920140621.html_df371131_tbl3.csv", "data\\raw\\cache\\tables\\081920140621.html_df371131_tbl4.csv", "data\\raw\\cache\\tables\\081920140621.html_df371131_tbl5.csv", "data\\raw\\cache\\tables\\081920140621.html_df371131_tbl6.csv", "data\\raw\\cache\\tables\\081920140621.html_df371131_tbl7.csv", "data\\raw\\cache\\tables\\081920140621.html_df371131_tbl8.csv"]}