{"url": "https://afltables.com/afl/stats/games/2008/091020080927.html", "fetched_at": 1769046583, "token": "091020080927.html_16232d65", "html_path": "data\\raw\\cache\\html\\091020080927.html_16232d65.html", "tables": ["data\\raw\\cache\\tables\\091020080927.html_16232d65_tbl0.csv", "data\\raw\\cache\\tables\\091020080927.html_16232d65_tbl1.csv", "data\\raw\\cache\\tables\\091020080927.html_16232d65_tbl2.csv", "data\\raw\\cache\\tables\\091020080927.html_16232d65_tbl3.csv", "data\\raw\\cache\\tables\\091020080927.html_16232d65_tbl4.csv", "data\\raw\\cache\\tables\\091020080927.html_16232d65_tbl5.csv", "data\\raw\\cache\\tables\\091020080927.html_16232d65_tbl6.csv", "data\\raw\\cache\\tables\\091020080927.html_16232d65_tbl7.csv"]}