{"url": "https://afltables.com/afl/stats/games/2024/091320240510.html", "fetched_at": 1769075062, "token": "091320240510.html_4ae02ac3", "html_path": "data\\raw\\cache\\html\\091320240510.html_4ae02ac3.html", "tables": ["data\\raw\\cache\\tables\\091320240510.html_4ae02ac3_tbl0.csv", "data\\raw\\cache\\tables\\091320240510.html_4ae02ac3_tbl1.csv", "data\\raw\\cache\\tables\\091320240510.html_4ae02ac3_tbl2.csv", "data\\raw\\cache\\tables\\091320240510.html_4ae02ac3_tbl3.csv", "data\\raw\\cache\\tables\\091320240510.html_4ae02ac3_tbl4.csv", "data\\raw\\cache\\tables\\091320240510.html_4ae02ac3_tbl5.csv", "data\\raw\\cache\\tables\\091320240510.html_4ae02ac3_tbl6.csv", "data\\raw\\cache\\tables\\091320240510.html_4ae02ac3_tbl7.csv"]}