{"url": "https://afltables.com/afl/stats/games/1997/091419970719.html", "fetched_at": 1761707772, "token": "091419970719.html_8dbff187", "html_path": "data\\raw\\cache\\html\\091419970719.html_8dbff187.html", "tables": ["data\\raw\\cache\\tables\\091419970719.html_8dbff187_tbl0.csv", "data\\raw\\cache\\tables\\091419970719.html_8dbff187_tbl1.csv", "data\\raw\\cache\\tables\\091419970719.html_8dbff187_tbl2.csv", "data\\raw\\cache\\tables\\091419970719.html_8dbff187_tbl3.csv", "data\\raw\\cache\\tables\\091419970719.html_8dbff187_tbl4.csv", "data\\raw\\cache\\tables\\091419970719.html_8dbff187_tbl5.csv", "data\\raw\\cache\\tables\\091419970719.html_8dbff187_tbl6.csv"]}