{"url": "https://afltables.com/afl/stats/games/1997/091919970525.html", "fetched_at": 1761707671, "token": "091919970525.html_09dd672e", "html_path": "data\\raw\\cache\\html\\091919970525.html_09dd672e.html", "tables": ["data\\raw\\cache\\tables\\091919970525.html_09dd672e_tbl0.csv", "data\\raw\\cache\\tables\\091919970525.html_09dd672e_tbl1.csv", "data\\raw\\cache\\tables\\091919970525.html_09dd672e_tbl2.csv", "data\\raw\\cache\\tables\\091919970525.html_09dd672e_tbl3.csv", "data\\raw\\cache\\tables\\091919970525.html_09dd672e_tbl4.csv", "data\\raw\\cache\\tables\\091919970525.html_09dd672e_tbl5.csv", "data\\raw\\cache\\tables\\091919970525.html_09dd672e_tbl6.csv"]}