{"url": "https://afltables.com/afl/stats/games/1993/101119930327.html", "fetched_at": 1761629904, "token": "101119930327.html_34b292cf", "html_path": "data\\raw\\cache\\html\\101119930327.html_34b292cf.html", "tables": ["data\\raw\\cache\\tables\\101119930327.html_34b292cf_tbl0.csv", "data\\raw\\cache\\tables\\101119930327.html_34b292cf_tbl1.csv", "data\\raw\\cache\\tables\\101119930327.html_34b292cf_tbl2.csv", "data\\raw\\cache\\tables\\101119930327.html_34b292cf_tbl3.csv", "data\\raw\\cache\\tables\\101119930327.html_34b292cf_tbl4.csv", "data\\raw\\cache\\tables\\101119930327.html_34b292cf_tbl5.csv", "data\\raw\\cache\\tables\\101119930327.html_34b292cf_tbl6.csv"]}