{"url": "https://afltables.com/afl/stats/games/1997/101219970503.html", "fetched_at": 1761707627, "token": "101219970503.html_235a9145", "html_path": "data\\raw\\cache\\html\\101219970503.html_235a9145.html", "tables": ["data\\raw\\cache\\tables\\101219970503.html_235a9145_tbl0.csv", "data\\raw\\cache\\tables\\101219970503.html_235a9145_tbl1.csv", "data\\raw\\cache\\tables\\101219970503.html_235a9145_tbl2.csv", "data\\raw\\cache\\tables\\101219970503.html_235a9145_tbl3.csv", "data\\raw\\cache\\tables\\101219970503.html_235a9145_tbl4.csv", "data\\raw\\cache\\tables\\101219970503.html_235a9145_tbl5.csv", "data\\raw\\cache\\tables\\101219970503.html_235a9145_tbl6.csv"]}