{"url": "https://afltables.com/afl/stats/games/2009/101320090802.html", "fetched_at": 1769046928, "token": "101320090802.html_95beeec9", "html_path": "data\\raw\\cache\\html\\101320090802.html_95beeec9.html", "tables": ["data\\raw\\cache\\tables\\101320090802.html_95beeec9_tbl0.csv", "data\\raw\\cache\\tables\\101320090802.html_95beeec9_tbl1.csv", "data\\raw\\cache\\tables\\101320090802.html_95beeec9_tbl2.csv", "data\\raw\\cache\\tables\\101320090802.html_95beeec9_tbl3.csv", "data\\raw\\cache\\tables\\101320090802.html_95beeec9_tbl4.csv", "data\\raw\\cache\\tables\\101320090802.html_95beeec9_tbl5.csv", "data\\raw\\cache\\tables\\101320090802.html_95beeec9_tbl6.csv", "data\\raw\\cache\\tables\\101320090802.html_95beeec9_tbl7.csv"]}