{"url": "https://afltables.com/afl/stats/games/2003/101520030601.html", "fetched_at": 1768777184, "token": "101520030601.html_24077a48", "html_path": "data\\raw\\cache\\html\\101520030601.html_24077a48.html", "tables": ["data\\raw\\cache\\tables\\101520030601.html_24077a48_tbl0.csv", "data\\raw\\cache\\tables\\101520030601.html_24077a48_tbl1.csv", "data\\raw\\cache\\tables\\101520030601.html_24077a48_tbl2.csv", "data\\raw\\cache\\tables\\101520030601.html_24077a48_tbl3.csv", "data\\raw\\cache\\tables\\101520030601.html_24077a48_tbl4.csv", "data\\raw\\cache\\tables\\101520030601.html_24077a48_tbl5.csv", "data\\raw\\cache\\tables\\101520030601.html_24077a48_tbl6.csv", "data\\raw\\cache\\tables\\101520030601.html_24077a48_tbl7.csv"]}