{"url": "https://afltables.com/afl/stats/games/1994/101619940612.html", "fetched_at": 1761631360, "token": "101619940612.html_c1deba28", "html_path": "data\\raw\\cache\\html\\101619940612.html_c1deba28.html", "tables": ["data\\raw\\cache\\tables\\101619940612.html_c1deba28_tbl0.csv", "data\\raw\\cache\\tables\\101619940612.html_c1deba28_tbl1.csv", "data\\raw\\cache\\tables\\101619940612.html_c1deba28_tbl2.csv", "data\\raw\\cache\\tables\\101619940612.html_c1deba28_tbl3.csv", "data\\raw\\cache\\tables\\101619940612.html_c1deba28_tbl4.csv", "data\\raw\\cache\\tables\\101619940612.html_c1deba28_tbl5.csv", "data\\raw\\cache\\tables\\101619940612.html_c1deba28_tbl6.csv"]}