{"url": "https://afltables.com/afl/stats/games/1998/111819980628.html", "fetched_at": 1761708313, "token": "111819980628.html_58fb23a7", "html_path": "data\\raw\\cache\\html\\111819980628.html_58fb23a7.html", "tables": ["data\\raw\\cache\\tables\\111819980628.html_58fb23a7_tbl0.csv", "data\\raw\\cache\\tables\\111819980628.html_58fb23a7_tbl1.csv", "data\\raw\\cache\\tables\\111819980628.html_58fb23a7_tbl2.csv", "data\\raw\\cache\\tables\\111819980628.html_58fb23a7_tbl3.csv", "data\\raw\\cache\\tables\\111819980628.html_58fb23a7_tbl4.csv", "data\\raw\\cache\\tables\\111819980628.html_58fb23a7_tbl5.csv", "data\\raw\\cache\\tables\\111819980628.html_58fb23a7_tbl6.csv"]}