{"url": "https://afltables.com/afl/stats/games/2024/121420240803.html", "fetched_at": 1769075261, "token": "121420240803.html_420e694b", "html_path": "data\\raw\\cache\\html\\121420240803.html_420e694b.html", "tables": ["data\\raw\\cache\\tables\\121420240803.html_420e694b_tbl0.csv", "data\\raw\\cache\\tables\\121420240803.html_420e694b_tbl1.csv", "data\\raw\\cache\\tables\\121420240803.html_420e694b_tbl2.csv", "data\\raw\\cache\\tables\\121420240803.html_420e694b_tbl3.csv", "data\\raw\\cache\\tables\\121420240803.html_420e694b_tbl4.csv", "data\\raw\\cache\\tables\\121420240803.html_420e694b_tbl5.csv", "data\\raw\\cache\\tables\\121420240803.html_420e694b_tbl6.csv", "data\\raw\\cache\\tables\\121420240803.html_420e694b_tbl7.csv"]}