{"url": "https://afltables.com/afl/stats/games/1990/121519900519.html", "fetched_at": 1761397051, "token": "121519900519.html_eabcc893", "html_path": "data\\raw\\cache\\html\\121519900519.html_eabcc893.html", "tables": ["data\\raw\\cache\\tables\\121519900519.html_eabcc893_tbl0.csv", "data\\raw\\cache\\tables\\121519900519.html_eabcc893_tbl1.csv", "data\\raw\\cache\\tables\\121519900519.html_eabcc893_tbl2.csv", "data\\raw\\cache\\tables\\121519900519.html_eabcc893_tbl3.csv", "data\\raw\\cache\\tables\\121519900519.html_eabcc893_tbl4.csv", "data\\raw\\cache\\tables\\121519900519.html_eabcc893_tbl5.csv", "data\\raw\\cache\\tables\\121519900519.html_eabcc893_tbl6.csv"]}