{"url": "https://afltables.com/afl/stats/games/2000/121520000422.html", "fetched_at": 1768773671, "token": "121520000422.html_2d6696e3", "html_path": "data\\raw\\cache\\html\\121520000422.html_2d6696e3.html", "tables": ["data\\raw\\cache\\tables\\121520000422.html_2d6696e3_tbl0.csv", "data\\raw\\cache\\tables\\121520000422.html_2d6696e3_tbl1.csv", "data\\raw\\cache\\tables\\121520000422.html_2d6696e3_tbl2.csv", "data\\raw\\cache\\tables\\121520000422.html_2d6696e3_tbl3.csv", "data\\raw\\cache\\tables\\121520000422.html_2d6696e3_tbl4.csv", "data\\raw\\cache\\tables\\121520000422.html_2d6696e3_tbl5.csv", "data\\raw\\cache\\tables\\121520000422.html_2d6696e3_tbl6.csv"]}