{"url": "https://afltables.com/afl/stats/games/2023/121520230507.html", "fetched_at": 1769074592, "token": "121520230507.html_b6f6c2b4", "html_path": "data\\raw\\cache\\html\\121520230507.html_b6f6c2b4.html", "tables": ["data\\raw\\cache\\tables\\121520230507.html_b6f6c2b4_tbl0.csv", "data\\raw\\cache\\tables\\121520230507.html_b6f6c2b4_tbl1.csv", "data\\raw\\cache\\tables\\121520230507.html_b6f6c2b4_tbl2.csv", "data\\raw\\cache\\tables\\121520230507.html_b6f6c2b4_tbl3.csv", "data\\raw\\cache\\tables\\121520230507.html_b6f6c2b4_tbl4.csv", "data\\raw\\cache\\tables\\121520230507.html_b6f6c2b4_tbl5.csv", "data\\raw\\cache\\tables\\121520230507.html_b6f6c2b4_tbl6.csv", "data\\raw\\cache\\tables\\121520230507.html_b6f6c2b4_tbl7.csv"]}