{"url": "https://afltables.com/afl/stats/games/2011/121620110528.html", "fetched_at": 1769059066, "token": "121620110528.html_2ee9b787", "html_path": "data\\raw\\cache\\html\\121620110528.html_2ee9b787.html", "tables": ["data\\raw\\cache\\tables\\121620110528.html_2ee9b787_tbl0.csv", "data\\raw\\cache\\tables\\121620110528.html_2ee9b787_tbl1.csv", "data\\raw\\cache\\tables\\121620110528.html_2ee9b787_tbl2.csv", "data\\raw\\cache\\tables\\121620110528.html_2ee9b787_tbl3.csv", "data\\raw\\cache\\tables\\121620110528.html_2ee9b787_tbl4.csv", "data\\raw\\cache\\tables\\121620110528.html_2ee9b787_tbl5.csv", "data\\raw\\cache\\tables\\121620110528.html_2ee9b787_tbl6.csv", "data\\raw\\cache\\tables\\121620110528.html_2ee9b787_tbl7.csv"]}