{"url": "https://afltables.com/afl/stats/games/2019/122120190616.html", "fetched_at": 1769072779, "token": "122120190616.html_59fdc710", "html_path": "data\\raw\\cache\\html\\122120190616.html_59fdc710.html", "tables": ["data\\raw\\cache\\tables\\122120190616.html_59fdc710_tbl0.csv", "data\\raw\\cache\\tables\\122120190616.html_59fdc710_tbl1.csv", "data\\raw\\cache\\tables\\122120190616.html_59fdc710_tbl2.csv", "data\\raw\\cache\\tables\\122120190616.html_59fdc710_tbl3.csv", "data\\raw\\cache\\tables\\122120190616.html_59fdc710_tbl4.csv", "data\\raw\\cache\\tables\\122120190616.html_59fdc710_tbl5.csv", "data\\raw\\cache\\tables\\122120190616.html_59fdc710_tbl6.csv", "data\\raw\\cache\\tables\\122120190616.html_59fdc710_tbl7.csv"]}