{"url": "https://afltables.com/afl/stats/games/2011/131420110528.html", "fetched_at": 1769059072, "token": "131420110528.html_71de7689", "html_path": "data\\raw\\cache\\html\\131420110528.html_71de7689.html", "tables": ["data\\raw\\cache\\tables\\131420110528.html_71de7689_tbl0.csv", "data\\raw\\cache\\tables\\131420110528.html_71de7689_tbl1.csv", "data\\raw\\cache\\tables\\131420110528.html_71de7689_tbl2.csv", "data\\raw\\cache\\tables\\131420110528.html_71de7689_tbl3.csv", "data\\raw\\cache\\tables\\131420110528.html_71de7689_tbl4.csv", "data\\raw\\cache\\tables\\131420110528.html_71de7689_tbl5.csv", "data\\raw\\cache\\tables\\131420110528.html_71de7689_tbl6.csv", "data\\raw\\cache\\tables\\131420110528.html_71de7689_tbl7.csv"]}