{"url": "https://afltables.com/afl/stats/games/2017/131620170325.html", "fetched_at": 1769071177, "token": "131620170325.html_de70f421", "html_path": "data\\raw\\cache\\html\\131620170325.html_de70f421.html", "tables": ["data\\raw\\cache\\tables\\131620170325.html_de70f421_tbl0.csv", "data\\raw\\cache\\tables\\131620170325.html_de70f421_tbl1.csv", "data\\raw\\cache\\tables\\131620170325.html_de70f421_tbl2.csv", "data\\raw\\cache\\tables\\131620170325.html_de70f421_tbl3.csv", "data\\raw\\cache\\tables\\131620170325.html_de70f421_tbl4.csv", "data\\raw\\cache\\tables\\131620170325.html_de70f421_tbl5.csv", "data\\raw\\cache\\tables\\131620170325.html_de70f421_tbl6.csv", "data\\raw\\cache\\tables\\131620170325.html_de70f421_tbl7.csv"]}