{"url": "https://afltables.com/afl/stats/games/2002/131820020824.html", "fetched_at": 1768776944, "token": "131820020824.html_41128858", "html_path": "data\\raw\\cache\\html\\131820020824.html_41128858.html", "tables": ["data\\raw\\cache\\tables\\131820020824.html_41128858_tbl0.csv", "data\\raw\\cache\\tables\\131820020824.html_41128858_tbl1.csv", "data\\raw\\cache\\tables\\131820020824.html_41128858_tbl2.csv", "data\\raw\\cache\\tables\\131820020824.html_41128858_tbl3.csv", "data\\raw\\cache\\tables\\131820020824.html_41128858_tbl4.csv", "data\\raw\\cache\\tables\\131820020824.html_41128858_tbl5.csv", "data\\raw\\cache\\tables\\131820020824.html_41128858_tbl6.csv", "data\\raw\\cache\\tables\\131820020824.html_41128858_tbl7.csv"]}