{"url": "https://afltables.com/afl/stats/games/2003/131920030405.html", "fetched_at": 1768777058, "token": "131920030405.html_336aa63a", "html_path": "data\\raw\\cache\\html\\131920030405.html_336aa63a.html", "tables": ["data\\raw\\cache\\tables\\131920030405.html_336aa63a_tbl0.csv", "data\\raw\\cache\\tables\\131920030405.html_336aa63a_tbl1.csv", "data\\raw\\cache\\tables\\131920030405.html_336aa63a_tbl2.csv", "data\\raw\\cache\\tables\\131920030405.html_336aa63a_tbl3.csv", "data\\raw\\cache\\tables\\131920030405.html_336aa63a_tbl4.csv", "data\\raw\\cache\\tables\\131920030405.html_336aa63a_tbl5.csv", "data\\raw\\cache\\tables\\131920030405.html_336aa63a_tbl6.csv", "data\\raw\\cache\\tables\\131920030405.html_336aa63a_tbl7.csv"]}