{"url": "https://afltables.com/afl/stats/games/2019/142120190714.html", "fetched_at": 1769072865, "token": "142120190714.html_a250743e", "html_path": "data\\raw\\cache\\html\\142120190714.html_a250743e.html", "tables": ["data\\raw\\cache\\tables\\142120190714.html_a250743e_tbl0.csv", "data\\raw\\cache\\tables\\142120190714.html_a250743e_tbl1.csv", "data\\raw\\cache\\tables\\142120190714.html_a250743e_tbl2.csv", "data\\raw\\cache\\tables\\142120190714.html_a250743e_tbl3.csv", "data\\raw\\cache\\tables\\142120190714.html_a250743e_tbl4.csv", "data\\raw\\cache\\tables\\142120190714.html_a250743e_tbl5.csv", "data\\raw\\cache\\tables\\142120190714.html_a250743e_tbl6.csv", "data\\raw\\cache\\tables\\142120190714.html_a250743e_tbl7.csv"]}