{"url": "https://afltables.com/afl/stats/games/2020/151620200801.html", "fetched_at": 1769073340, "token": "151620200801.html_af08704d", "html_path": "data\\raw\\cache\\html\\151620200801.html_af08704d.html", "tables": ["data\\raw\\cache\\tables\\151620200801.html_af08704d_tbl0.csv", "data\\raw\\cache\\tables\\151620200801.html_af08704d_tbl1.csv", "data\\raw\\cache\\tables\\151620200801.html_af08704d_tbl2.csv", "data\\raw\\cache\\tables\\151620200801.html_af08704d_tbl3.csv", "data\\raw\\cache\\tables\\151620200801.html_af08704d_tbl4.csv", "data\\raw\\cache\\tables\\151620200801.html_af08704d_tbl5.csv", "data\\raw\\cache\\tables\\151620200801.html_af08704d_tbl6.csv", "data\\raw\\cache\\tables\\151620200801.html_af08704d_tbl7.csv"]}