{"url": "https://afltables.com/afl/stats/games/2015/182020150516.html", "fetched_at": 1769070036, "token": "182020150516.html_9bdfbfe8", "html_path": "data\\raw\\cache\\html\\182020150516.html_9bdfbfe8.html", "tables": ["data\\raw\\cache\\tables\\182020150516.html_9bdfbfe8_tbl0.csv", "data\\raw\\cache\\tables\\182020150516.html_9bdfbfe8_tbl1.csv", "data\\raw\\cache\\tables\\182020150516.html_9bdfbfe8_tbl2.csv", "data\\raw\\cache\\tables\\182020150516.html_9bdfbfe8_tbl3.csv", "data\\raw\\cache\\tables\\182020150516.html_9bdfbfe8_tbl4.csv", "data\\raw\\cache\\tables\\182020150516.html_9bdfbfe8_tbl5.csv", "data\\raw\\cache\\tables\\182020150516.html_9bdfbfe8_tbl6.csv", "data\\raw\\cache\\tables\\182020150516.html_9bdfbfe8_tbl7.csv"]}