{"url": "https://afltables.com/afl/stats/games/2023/192020230520.html", "fetched_at": 1769074620, "token": "192020230520.html_670fbef9", "html_path": "data\\raw\\cache\\html\\192020230520.html_670fbef9.html", "tables": ["data\\raw\\cache\\tables\\192020230520.html_670fbef9_tbl0.csv", "data\\raw\\cache\\tables\\192020230520.html_670fbef9_tbl1.csv", "data\\raw\\cache\\tables\\192020230520.html_670fbef9_tbl2.csv", "data\\raw\\cache\\tables\\192020230520.html_670fbef9_tbl3.csv", "data\\raw\\cache\\tables\\192020230520.html_670fbef9_tbl4.csv", "data\\raw\\cache\\tables\\192020230520.html_670fbef9_tbl5.csv", "data\\raw\\cache\\tables\\192020230520.html_670fbef9_tbl6.csv", "data\\raw\\cache\\tables\\192020230520.html_670fbef9_tbl7.csv"]}